lakai/__init__.py
lakai/py.typed
lakai-0.1.2.dist-info/LICENSE
lakai-0.1.2.dist-info/WHEEL
lakai-0.1.2.dist-info/METADATA
lakai-0.1.2.dist-info/RECORD
