Metadata-Version: 2.1
Name: lakai
Version: 0.1.2
Summary: 
License: MIT
Author: Niklas Rosenstein
Author-email: rosensteinniklas@gmail.com
Requires-Python: >=3.6,<4.0
Classifier: License :: OSI Approved :: MIT License
Classifier: Programming Language :: Python :: 3
Classifier: Programming Language :: Python :: 3.6
Classifier: Programming Language :: Python :: 3.7
Classifier: Programming Language :: Python :: 3.8
Classifier: Programming Language :: Python :: 3.9
Classifier: Programming Language :: Python :: 3.10
Requires-Dist: dataclasses (>=0.6,<0.7)
Requires-Dist: lark (>=1.1.2,<2.0.0)
Requires-Dist: setuptools (>=30.1.0)
Requires-Dist: typing-extensions (>=3.0.0.0)
